Workbook

Sheet 2-功能点辅助规划（内部用不对外）
A1: 芜湖市智慧信用综合监管系统
A2: 序号 | B2: 应用系统名称 | C2: 功能点计数合计 | D2: 功能点数 | O2: 人工成本
D3: 功能点计数项 | E3: 功能点计数项数量 F | F3: 功能点权重值 P | G3: 未调整功点数 UFP=F*P | H3: 功能点数 合计S | I3: 功能点数 | J3: 工作量合计 (月) | K3: 基准人工费 （万元/月） | L3: 人月费用调整 | M3: 合计费用 （万元） | N3: 预估金额 (万元） | O3: 功能点计数项费用占比
A4: 合计
A5: 一 | B5: 服务业评价综合管理系统
A6: 1 | B6: 部门看板
A7: 1.1 | B7: 看板展示 | C7: =SUM(E7:E11) -> 28 | D7: ILF | E7: =INT((P7/K7/L7*176/'2-项目参数'!$E$14)/F7) -> 8 | F7: 35 | G7: =E7*F7 -> 280 | H7: =SUM(G7:G10) -> 580 | I7: =H7 -> 580 | J7: =ROUND(I7*'2-项目参数'!E14/176,4) -> 32.0568 | K7: 2.1015 | L7: 1 | M7: =J7*K7*L7 -> 67.367365 | N7: 70 | O7: 0.5 | P7: =N7*O7 -> 35
D8: EIF | E8: =INT((P8/K7/L7*176/'2-项目参数'!$E$14)/F8) -> 20 | F8: 15 | G8: =E8*F8 -> 300 | O8: 0.5 | P8: =N7*O8 -> 35
D9: EI | E9: =INT((P9/K7/L7*176/'2-项目参数'!$E$14)/F9) -> 0 | F9: 4 | G9: =E9*F9 -> 0 | O9: 0 | P9: =N7*O9 -> 0
D10: EO | E10: =INT((P10/K7/L7*176/'2-项目参数'!$E$14)/F10) -> 0 | F10: 5 | G10: =E10*F10 -> 0 | O10: 0 | P10: =N7*O10 -> 0
D11: EQ | E11: =INT((P11/K7/L7*176/'2-项目参数'!$E$14)/F11) -> 0 | F11: 4 | G11: =E11*F11 -> 0 | O11: 0 | P11: =N7*O11 -> 0
A12: 1.2 | B12: 看板展示2 | C12: =SUM(E12:E16) -> 1 | D12: ILF | E12: =INT((P12/K12/L12*176/'2-项目参数'!$E$14)/F12) -> 0 | F12: 35 | G12: =E12*F12 -> 0 | H12: =SUM(G12:G15) -> 15 | I12: =H12 -> 15 | J12: =ROUND(I12*'2-项目参数'!$E$14/176,4) -> 0.8291 | K12: 2.1015 | L12: 1 | M12: =J12*K12*L12 -> 1.7423537 | N12: 5 | O12: 0.5 | P12: =N12*O12 -> 2.5
D13: EIF | E13: =INT((P13/K12/L12*176/'2-项目参数'!$E$14)/F13) -> 1 | F13: 15 | G13: =E13*F13 -> 15 | O13: 0.5 | P13: =N12*O13 -> 2.5
D14: EI | E14: =INT((P14/K12/L12*176/'2-项目参数'!$E$14)/F14) -> 0 | F14: 4 | G14: =E14*F14 -> 0 | O14: 0 | P14: =N12*O14 -> 0
D15: EO | E15: =INT((P15/K12/L12*176/'2-项目参数'!$E$14)/F15) -> 0 | F15: 5 | G15: =E15*F15 -> 0 | O15: 0 | P15: =N12*O15 -> 0
D16: EQ | E16: =INT((P16/K12/L12*176/'2-项目参数'!$E$14)/F16) -> 0 | F16: 4 | G16: =E16*F16 -> 0 | O16: 0 | P16: =N12*O16 -> 0
A17: 2 | B17: 评价结果
A18: 2.1 | B18: 亩均一张图 | C18: =SUM(E18:E22) -> 20 | D18: ILF | E18: =INT((P18/K18/L18*176/'2-项目参数'!$E$14)/F18) -> 6 | F18: 35 | G18: =E18*F18 -> 210 | H18: =SUM(G18:G21) -> 420 | I18: =H18 -> 420 | J18: =ROUND(I18*'2-项目参数'!$E$14/176,4) -> 23.2135 | K18: 2.1015 | L18: 1 | M18: =J18*K18*L18 -> 48.78317 | N18: 50 | O18: 0.5 | P18: =N18*O18 -> 25
D19: EIF | E19: =INT((P19/K18/L18*176/'2-项目参数'!$E$14)/F19) -> 14 | F19: 15 | G19: =E19*F19 -> 210 | O19: 0.5 | P19: =N18*O19 -> 25
D20: EI | E20: =INT((P20/K18/L18*176/'2-项目参数'!$E$14)/F20) -> 0 | F20: 4 | G20: =E20*F20 -> 0 | O20: 0 | P20: =N18*O20 -> 0
D21: EO | E21: =INT((P21/K18/L18*176/'2-项目参数'!$E$14)/F21) -> 0 | F21: 5 | G21: =E21*F21 -> 0 | O21: 0 | P21: =N18*O21 -> 0
D22: EQ | E22: =INT((P22/K18/L18*176/'2-项目参数'!$E$14)/F22) -> 0 | F22: 4 | G22: =E22*F22 -> 0 | O22: 0 | P22: =N18*O22 -> 0
A23: 二 | B23: 模型管理(市级)
A24: 1 | B24: 数据模型AABB
A25: 1.1 | B25: 评价结果统计 | C25: =SUM(E25:E29) -> 0 | D25: ILF | E25: =INT((P25/K25/L25*176/'2-项目参数'!$E$14)/F25) -> 0 | F25: 35 | G25: =E25*F25 -> 0 | H25: =SUM(G25:G28) -> 0 | I25: =H25 -> 0 | J25: =ROUND(I25*'2-项目参数'!$E$14/176,4) -> 0 | K25: 2.1015 | L25: 1 | M25: =J25*K25*L25 -> 0 | N25: 3 | O25: 0.5 | P25: =N25*O25 -> 1.5
D26: EIF | E26: =INT((P26/K25/L25*176/'2-项目参数'!$E$14)/F26) -> 0 | F26: 15 | G26: =E26*F26 -> 0 | O26: 0.5 | P26: =N25*O26 -> 1.5
D27: EI | E27: =INT((P27/K25/L25*176/'2-项目参数'!$E$14)/F27) -> 0 | F27: 4 | G27: =E27*F27 -> 0 | O27: 0 | P27: =N25*O27 -> 0
D28: EO | E28: =INT((P28/K25/L25*176/'2-项目参数'!$E$14)/F28) -> 0 | F28: 5 | G28: =E28*F28 -> 0 | O28: 0 | P28: =N25*O28 -> 0
D29: EQ | E29: =INT((P29/K25/L25*176/'2-项目参数'!$E$14)/F29) -> 0 | F29: 4 | G29: =E29*F29 -> 0 | O29: 0 | P29: =N25*O29 -> 0

Sheet 2-项目参数
B2: 项目参数设定 | H2: 应用类型调整因子参数表
B3: 应用类型调整因子 | D3: 业务处理 | F3: =AVERAGEIFS(J4:J11,H4:H11,D3) -> 1 | H3: 应用类型 | I3: 范围 | J3: 调整因子
B4: 质量特征调整因子 | C4: 分布式处理 | D4: 在多个服务器及处理器上同时相互执行应用中的处理功能 | E4: =AVERAGEIFS(J27:J29,I27:I29,D4) -> 1 | F4: =SUM(E4:E7)*0.025+1 -> 1.075 | H4: 业务处理 | I4: 办公自动化系统；人事、会计、工资、销售等经营管理及业务处理用软件等 | J4: 1
C5: 性能 | D5: 为满足性能需求事项，要求设计阶段进行性能分析，或在设计、开发阶段使用分析工具 | E5: =AVERAGEIFS(J30:J32,I30:I32,D5) -> 1 | H5: 应用集成 | I5: 企业服务总线、应用集成等 | J5: 1.2
C6: 可靠性 | D6: 发生故障时可轻易修复，带来一定不便或经济损失 | E6: =AVERAGEIFS(J33:J35,I33:I35,D6) -> 0 | H6: 科技 | I6: 科学计算、模拟、统计等 | J6: 1.2
C7: 多重站点 | D7: 在不同用途的硬件或软件环境下运行 | E7: =AVERAGEIFS(J36:J38,I36:I38,D7) -> 1 | H7: 多媒体 | I7: 图形、影像、声音等多媒体应用领域；地理信息系统；教育和娱乐应用等 | J7: 1.3
B8: 开发语言调整因子 | D8: JAVA、C++、C#及其他同级别语言/平台 | F8: =AVERAGEIFS(J15:J17,H15:H17,D8) -> 1 | H8: 智能信息 | I8: 自然语言处理、人工智能、专家系统等 | J8: 1.7
B9: 复用度调整系数 | F9: 1 | H9: 系统 | I9: 操作系统、数据库系统、集成开发环境、自动化开发/设计工具等 | J9: 1.7
B10: 规模变更调整因子 | D10: 项目预估阶段 | F10: =AVERAGEIFS(J43:J44,H43:H44,D10) -> 1.39 | H10: 通信控制 | I10: 通信协议、仿真、交换机软件、全球定位系统等 | J10: 1.9
B11: 开发团队背景调整因子 | D11: 为其他行业开发过类似的项目，或为本行业开发过不同但相关的项目 | F11: =AVERAGEIFS(J20:J22,H20:H22,D11) -> 1 | H11: 流程控制 | I11: 生产管理、仪器控制、机器人控制、实时控制、嵌入式软件等 | J11: 2
B12: 单功能点耗时率 | D12: =F12 -> 6.51 | F12: 6.51
B13: 基准人月费用 | D13: 21015 | F13: =D13 -> 21015 | H13: 开发语言调整因子参数表
B14: 参考《DB11T1010-2019信息化项目软件开发费用测算规范（发布稿）》 CSBMK-2020年中国软件行业基准数据 | E14: =PRODUCT(F3:F12) -> 9.7275675 | H14: 语言分类 | J14: 调整因子
H15: C及其他同级别语言/平台 | J15: 1.5
H16: JAVA、C++、C#及其他同级别语言/平台 | J16: 1
H17: PowerBuilder、ASP及其他同级别语言/平台 | J17: 0.6
H19: 开发团队背景调整因子参数表
H20: 判断标准 | J20: 影响度
H21: 为本行业开发过类似的项目 | J21: 0.8
H22: 为其他行业开发过类似的项目，或为本行业开发过不同但相关的项目 | J22: 1
H23: 没有同类项目的背景 | J23: 1.2
H26: 质量特征调整因子参数表
H27: 分布式处理 | I27: 没有明示对分布式处理的需求事项 | J27: -1
I28: 通过网络进行客户端/服务器及网络基础应用分布处理和传输 | J28: 0
I29: 在多个服务器及处理器上同时相互执行应用中的处理功能 | J29: 1
H30: 性能 | I30: 没有明示对性能的特别需求事项或活动，因此提供基本性能 | J30: -1
I31: 应答时间或处理率对高峰时间或所有业务时间都很重要，对连动系统结束处理时间有限制 | J31: 0
I32: 为满足性能需求事项，要求设计阶段进行性能分析，或在设计、开发阶段使用分析工具 | J32: 1
H33: 可靠性 | I33: 没有明示对可靠性的特别需求事项或活动，因此提供基本的可靠性 | J33: -1
I34: 发生故障时可轻易修复，带来一定不便或经济损失 | J34: 0
I35: 发生故障时很难修复，发生重大经济损失或有生命危害 | J35: 1
H36: 多重站点 | I36: 在相同用途的硬件或软件环境下运行 | J36: -1
I37: 在用途类似的硬件或软件环境下运行 | J37: 0
I38: 在不同用途的硬件或软件环境下运行 | J38: 1
H39: 注：质量特性调整因子=（分布式处理因子 + 性能因子 + 可靠性因子 + 多重站点因子）×0.025 + 1
H42: 规模调整因子参数表
H43: 项目预估阶段 | J43: 1.39
H44: 项目估算阶段（投标） | J44: 1.22

Sheet 2-直接非人力成本测算表
A1: 直接非人力成本测算表
A2: 序号 | B2: 分项 | C2: 金额（元） | D2: 备注 | E2: 说明
A3: 1 | B3: 办公费 | C3: 3000 | E3: 开发方为开发此项目而产生的行政办公费用，如办公用品、通讯、邮寄、印刷、会议等。 示例 1：项目成员因项目加班而产生的餐费宜计入直接非人力成本中的办公费，而项目成员的工作午餐费宜计入直接人力成本。 示例 2：项目组封闭开发租用会议室而产生的费用宜计入直接非人力成本中的办公费，而研发部例会租用会议室产生的费用宜按照间接非人力成本。
A4: 2 | B4: 差旅费 | C4: 2000 | E4: 开发方为开发此项目而产生的差旅费用，如交通、住宿、差旅补贴等。
A5: 3 | B5: 培训费 | C5: 0 | E5: 开发方为开发此项目而安排的培训产生的费用。
A6: 4 | B6: 业务费 | C6: 5000 | E6: 开发方为完成此项目开发工作所需辅助活动产生的费用，如评审费、验收费等。
A7: 5 | B7: 采购费 | C7: 0 | E7: 开发方为开发此项目而需特殊采购专用资产或服务的费用，如专用设备费、专用软件费、技术协作费、专利费等。示例：为项目采购专用测试软件的成本宜计入直接非人力成本中的采购费，日常办公用软件的成本宜按照间接非人力成本进行分摊。
A8: 6 | B8: 其它 | E8: 未在以上项目列出但确系开发方为开发此项目所需花费的费用。
A9: 合计 | C9: =SUM(C3:C8) -> 10000 | D9: 测算责任人： 测算日期： 年 月 日

Sheet 2-功能点清单
A1: 序号 | B1: 应用系统名称 | C1: 功能点计数项名称 | D1: 功能点计数项类别 | E1: 重用程度
A3: 合计 | C3: =COUNTA(C4:C47) -> 0 | D3: =COUNTA(D4:D47) -> 41 | E3: =COUNTA(E4:E47) -> 41
A4: 一 | B4: XXX系统
A5: 1 | B5: XXX子系统
A6: 1.1 | B6: XXX功能 | D6: ILF | E6: 低
D7: EQ | E7: 低
D8: ILF | E8: 低
D9: EO | E9: 低
D10: ILF | E10: 低
D11: ILF | E11: 低
D12: EO | E12: 低
D13: ILF | E13: 低
B14: XXX功能 | D14: ILF | E14: 低
D15: EO | E15: 低
D16: EO | E16: 低
D17: EO | E17: 低
D18: ILF | E18: 低
D19: ILF | E19: 低
D20: ILF | E20: 低
D21: ILF | E21: 低
D22: EIF | E22: 低
D23: ILF | E23: 低
D24: ILF | E24: 中
A25: 2 | B25: XXX子系统
A26: 2.1 | D26: EQ | E26: 低
D27: ILF | E27: 低
D28: ILF | E28: 低
D29: ILF | E29: 低
D30: ILF | E30: 低
D31: ILF | E31: 低
D32: ILF | E32: 低
D33: ILF | E33: 低
D34: ILF | E34: 低
D35: ILF | E35: 低
D36: ILF | E36: 低
D37: ILF | E37: 低
D38: EQ | E38: 低
... D47: ILF | E47: 中

Sheet 2-软件计算过程-预估规模
A1: 预估规模 | H1: 功能点预估规模、工作量、费用表
A2: 功能类型 | B2: 不同复用度文件数 | D2: 功能点数 | E2: 功能点数合计 | H2: 1.未调整功能点数 UFP（功能点） | J2: =E11 -> 999
A3: ILF | B3: 低 | C3: =COUNTIFS('2-功能点清单'!$C$4:$C$513,"<> ",'2-功能点清单'!$D$4:$D$513,'2-软件计算过程-估算规模'!A3,'2-功能点清单'!$E$4:$E$513,'2-软件计算过程-预估规模'!B3) -> 26 | D3: =ROUND(C3*1*35,0) -> 910 | E3: =ROUND((D3+D4+D5),0) -> 969 | H3: 经过复用调整后的功能点数 US（功能点） | J3: -
B4: 中 | C4: =COUNTIFS('2-功能点清单'!$C$4:$C$513,"<> ",'2-功能点清单'!$D$4:$D$513,'2-软件计算过程-估算规模'!A3,'2-功能点清单'!$E$4:$E$513,'2-软件计算过程-预估规模'!B4) -> 2 | D4: =ROUND(C4*2/3*35,0) -> 47 | H4: 设定规模变更因子 CF | J4: ='2-项目参数'!F10 -> 1.39
B5: 高 | C5: =COUNTIFS('2-功能点清单'!$C$4:$C$513,"<> ",'2-功能点清单'!$D$4:$D$513,'2-软件计算过程-估算规模'!A3,'2-功能点清单'!$E$4:$E$513,'2-软件计算过程-预估规模'!B5) -> 1 | D5: =ROUND(C5*1/3*35,0) -> 12 | H5: 2.调整后的功能点数 S（功能点） | I5: S=UFP×CF（不调整复用度） | J5: =J4*J2 -> 1388.61
B6: ILF合计
A7: EIF | B7: 低 | C7: =COUNTIFS('2-功能点清单'!$C$4:$C$513,"<> ",'2-功能点清单'!$D$4:$D$513,A7,'2-功能点清单'!$E$4:$E$513,'2-软件计算过程-预估规模'!B7) -> 2 | D7: =ROUND(C7*1*15,0) -> 30 | E7: =D7+D8+D9 -> 30 | I7: S=US×CF（调整复用度） | J7: -
B8: 中 | C8: =COUNTIFS('2-功能点清单'!$C$4:$C$513,"<> ",'2-功能点清单'!$D$4:$D$513,A7,'2-功能点清单'!$E$4:$E$513,'2-软件计算过程-预估规模'!B8) -> 0 | D8: =ROUND(C8*(2/3)*15,0) -> 0 | H8: 基准数据（生产率） | I8: P25（人时/功能点） | J8: =0.75*J9 -> 4.8825
B9: 高 | C9: =COUNTIFS('2-功能点清单'!$C$4:$C$513,"<> ",'2-功能点清单'!$D$4:$D$513,A7,'2-功能点清单'!$E$4:$E$513,'2-软件计算过程-预估规模'!B9) -> 0 | D9: =ROUND(C9*(1/3)*15,0) -> 0 | I9: P50（人时/功能点） | J9: ='2-项目参数'!F12 -> 6.51
B10: EIF合计 | I10: P75（人时/功能点） | J10: =1.25*J9 -> 8.1375
A11: US（ILF计数合计+ EIF计数合计） | E11: =E3+E7 -> 999 | H11: 3.未调整的工作量 UE（人时） 计算公式：UE=PDR×S | I11: 下限（人时） | J11: =J5*J8 -> 6779.8883
A12: 规模变更调整因子： | E12: 1.39 | I12: 最有可能（人时） | J12: =J5*J9 -> 9039.8511
A13: S（调整后规模总计）： | E13: =ROUND(E11*E12,0) -> 1389 | I13: 上限（人时） | J13: =J5*J10 -> 11299.814
A14: 该部分的整体复用程度是开发方开发过类似功能 | H14: 设定调整因子 | I14: 应用类型调整因子 AT | J14: ='2-项目参数'!F3 -> 1
I15: 质量特征调整因子 QR | J15: ='2-项目参数'!F4 -> 1.075
I16: 开发语言调整因子 SL | J16: ='2-项目参数'!F8 -> 1
I17: 开发团队背景调整因子 DT | J17: ='2-项目参数'!F11 -> 1
H18: 4.调整后的工作量 AE（人时） 计算公式：AE=UE×SWF×RDF； 其中 SWF=AT×QR，RDF=SL×DT | I18: 下限（人时） | J18: =PRODUCT(J14:J17)*J11 -> 7288.3799
I19: 最有可能（人时） | J19: =PRODUCT(J14:J17)*J12 -> 9717.8399
I20: 上限（人时） | J20: =PRODUCT(J14:J17)*J13 -> 12147.3
H21: 人月折算系数 HM（人时/人月） | J21: 176
H22: 平均人力成本费率（含直接人力成本和间接成本+开发方毛利润）F（元/人月） | J22: ='2-项目参数'!F13 -> 21015
H23: 直接非人力成本合计 DNC（元） | J23: ='2-直接非人力成本测算表'!$C$9 -> 10000
H24: 5.软件开发费用（元） 计算公式：P=AE/HM×F +DNC | I24: 下限（元） | J24: =ROUND(J18/J21*J22+J23,2) -> 880257.41
I25: 最有可能（元） | J25: =ROUND(J19/J21*J22+J23,2) -> 1170343.2
I26: 上限（元） | J26: =ROUND(J20/J21*J22+J23,2) -> 1460429
I27: 最终费用/价格（元） | J27: =J25 -> 1170343.2
I28: 功能点单价（元/功能点） | J28: =ROUND((J27-J23)/J5,2) -> 835.61

Sheet 2-软件计算过程-估算规模
A1: 测算规模 | G1: 功能点测算规模、工作量、费用表
A2: 功能类型 | B2: 不同复用度文件数 | D2: 功能点数 | E2: 功能点数合计 | G2: 1.未调整功能点数 UFP（功能点） | I2: =E18 -> 335
A3: ILF | B3: 低 | C3: =COUNTIFS('2-功能点清单'!$C$4:$C$513,"<> ",'2-功能点清单'!$D$4:$D$513,A3,'2-功能点清单'!$E$4:$E$513,B3) -> 26 | D3: =ROUND(C3*1*10,0) -> 260 | E3: =ROUND((D3+D4+D5),0) -> 276 | G3: 经过复用调整后的功能点数 US（功能点） | I3: =I2*'2-项目参数'!F9 -> 335
B4: 中 | C4: =COUNTIFS('2-功能点清单'!$C$4:$C$513,"<> ",'2-功能点清单'!$D$4:$D$513,A3,'2-功能点清单'!$E$4:$E$513,B4) -> 2 | D4: =ROUND(C4*(2/3)*10,0) -> 13 | G4: 设定规模变更因子 CF | I4: ='2-项目参数'!F10 -> 1.39
B5: 高 | C5: =COUNTIFS('2-功能点清单'!$C$4:$C$513,"<> ",'2-功能点清单'!$D$4:$D$513,A3,'2-功能点清单'!$E$4:$E$513,B5) -> 1 | D5: =ROUND(C5*(1/3)*10,0) -> 3 | G5: 2.调整后的功能点数 S（功能点） | H5: S=UFP×CF（不调整复用度） | I5: =I4*I2 -> 465.65
A6: EIF | B6: 低 | C6: =COUNTIFS('2-功能点清单'!$C$4:$C$513,"<> ",'2-功能点清单'!$D$4:$D$513,A6,'2-功能点清单'!$E$4:$E$513,B6) -> 2 | D6: =ROUND(C6*1*7,0) -> 14 | E6: =D6+D7+D8 -> 14 | H6: S=US×CF（调整复用度） | I6: =I4*I3 -> 465.65
B7: 中 | C7: =COUNTIFS('2-功能点清单'!$C$4:$C$513,"<> ",'2-功能点清单'!$D$4:$D$513,A6,'2-功能点清单'!$E$4:$E$513,B7) -> 0 | D7: =ROUND(C7*(2/3)*7,0) -> 0 | G7: 基准数据（生产率） | H7: P25（人时/功能点） | I7: =ROUND(I8*0.75,2) -> 4.88
B8: 高 | C8: =COUNTIFS('2-功能点清单'!$C$4:$C$513,"<> ",'2-功能点清单'!$D$4:$D$513,A6,'2-功能点清单'!$E$4:$E$513,B8) -> 0 | D8: =ROUND(C8*(1/3)*7,0) -> 0 | H8: P50（人时/功能点） | I8: ='2-项目参数'!F12 -> 6.51
A9: EI | B9: 低 | C9: =COUNTIFS('2-功能点清单'!$C$4:$C$513,"<> ",'2-功能点清单'!$D$4:$D$513,A9,'2-功能点清单'!$E$4:$E$513,B9) -> 2 | D9: =ROUND(C9*1*4,0) -> 8 | E9: =D9+D10+D11 -> 8 | H9: P75（人时/功能点） | I9: =ROUND(I8*1.25,2) -> 8.14
B10: 中 | C10: =COUNTIFS('2-功能点清单'!$C$4:$C$513,"<> ",'2-功能点清单'!$D$4:$D$513,A9,'2-功能点清单'!$E$4:$E$513,B10) -> 0 | D10: =ROUND(C10*(2/3)*4,0) -> 0 | G10: 3.未调整的工作量 UE（人时） 计算公式：UE=PDR×S | H10: 下限（人时） | I10: =I6*I7 -> 2272.372
B11: 高 | C11: =COUNTIFS('2-功能点清单'!$C$4:$C$513,"<> ",'2-功能点清单'!$D$4:$D$513,A9,'2-功能点清单'!$E$4:$E$513,B11) -> 0 | D11: =ROUND(C11*(1/3)*4,0) -> 0 | H11: 最有可能（人时） | I11: =I6*I8 -> 3031.3815
A12: EO | B12: 低 | C12: =COUNTIFS('2-功能点清单'!$C$4:$C$513,"<> ",'2-功能点清单'!$D$4:$D$513,A12,'2-功能点清单'!$E$4:$E$513,B12) -> 5 | D12: =ROUND(C12*1*5,0) -> 25 | E12: =D12+D13+D14 -> 25 | H12: 上限（人时） | I12: =I6*I9 -> 3790.391
B13: 中 | C13: =COUNTIFS('2-功能点清单'!$C$4:$C$513,"<> ",'2-功能点清单'!$D$4:$D$513,A12,'2-功能点清单'!$E$4:$E$513,B13) -> 0 | D13: =ROUND(C13*(2/3)*5,0) -> 0 | G13: 设定调整因子 | H13: 应用类型调整因子 AT | I13: ='2-项目参数'!F3 -> 1
B14: 高 | C14: =COUNTIFS('2-功能点清单'!$C$4:$C$513,"<> ",'2-功能点清单'!$D$4:$D$513,A12,'2-功能点清单'!$E$4:$E$513,B14) -> 0 | D14: =ROUND(C14*(1/3)*5,0) -> 0 | H14: 质量特征调整因子 QR | I14: ='2-项目参数'!F4 -> 1.075
A15: EQ | B15: 低 | C15: =COUNTIFS('2-功能点清单'!$C$4:$C$513,"<> ",'2-功能点清单'!$D$4:$D$513,A15,'2-功能点清单'!$E$4:$E$513,B15) -> 3 | D15: =ROUND(C15*1*4,0) -> 12 | E15: =D15+D16+D17 -> 12 | H15: 开发语言调整因子 SL | I15: ='2-项目参数'!F8 -> 1
B16: 中 | C16: =COUNTIFS('2-功能点清单'!$C$4:$C$513,"<> ",'2-功能点清单'!$D$4:$D$513,A15,'2-功能点清单'!$E$4:$E$513,B16) -> 0 | D16: =ROUND(C16*(2/3)*4,0) -> 0 | H16: 开发团队背景调整因子 DT | I16: ='2-项目参数'!F11 -> 1
B17: 高 | C17: =COUNTIFS('2-功能点清单'!$C$4:$C$513,"<> ",'2-功能点清单'!$D$4:$D$513,A15,'2-功能点清单'!$E$4:$E$513,B17) -> 0 | D17: =ROUND(C17*(1/3)*4,0) -> 0 | G17: 4.调整后的工作量 AE（人时） 计算公式：AE=UE×SWF×RDF； 其中 SWF=AT×QR，RDF=SL×DT | H17: 下限（人时） | I17: =PRODUCT(I13:I16)*I10 -> 2442.7999
A18: US（ILF计数合计+ EIF计数合计） | E18: =E3+E6+E9+E12+E15 -> 335 | H18: 最有可能（人时） | I18: =PRODUCT(I13:I16)*I11 -> 3258.7351
A19: 规模变更调整因子： | E19: ='2-项目参数'!F10 -> 1.39 | H19: 上限（人时） | I19: =PRODUCT(I13:I16)*I12 -> 4074.6703
A20: S（调整后规模总计）： | E20: =ROUND(E18*E19,0) -> 466 | G20: 人月折算系数 HM（人时/人月） | I20: 176
G21: 平均人力成本费率（含直接人力成本和间接成本+开发方毛利润）F（元/人月） | I21: ='2-项目参数'!F13 -> 21015
G22: 直接非人力成本合计 DNC（元） | I22: ='2-直接非人力成本测算表'!$C$9 -> 10000
G23: 5.软件开发费用（元） 计算公式：P=AE/HM×F +DNC | H23: 下限（元） | I23: =ROUND(I17/I20*I21+I22,2) -> 301678.64
H24: 最有可能（元） | I24: =ROUND(I18/I20*I21+I22,2) -> 399104.08
H25: 上限（元） | I25: =ROUND(I19/I20*I21+I22,2) -> 496529.53
H26: 最终费用/价格（元） | I26: =I24 -> 399104.08
H27: 功能点单价（元/功能点） | I27: =ROUND(I24/I6,2) -> 857.09
